README
setup.py
gkraz/__init__.py
gkraz/__main__.py
gkraz/bytecode.py
gkraz/errors.py
gkraz/functions.py
gkraz/highlightlexer.py
gkraz/lexer.py
gkraz/output.py
gkraz/parser.py
gkraz/runtime.py
gkraz.egg-info/PKG-INFO
gkraz.egg-info/SOURCES.txt
gkraz.egg-info/dependency_links.txt
gkraz.egg-info/entry_points.txt
gkraz.egg-info/not-zip-safe
gkraz.egg-info/requires.txt
gkraz.egg-info/top_level.txt