Metadata-Version: 1.0
Name: gkraz
Version: 0.1
Summary: Calculator for the terminal
Home-page: http://theovention.de
Author: Theo Heimel
Author-email: info@theovention.de
License: MIT
Platform: UNKNOWN
